{
	"id": "959261b9-17c7-4a55-96ba-f07282547661",
	"name": "PreProd",
	"values": [
		{
			"key": "endpoint",
			"value": "api/register/preprod",
			"description": "",
			"enabled": true
		},
		{
			"key": "email",
			"value": "sydney_preprod@fife",
			"description": "",
			"enabled": true
		},
		{
			"key": "password",
			"value": "pistol_preprod",
			"description": "",
			"enabled": true
		}
	],
	"_postman_variable_scope": "environment",
	"_postman_exported_at": "2019-01-21T18:45:45.823Z",
	"_postman_exported_using": "Postman/6.5.2"
}